README.md
pyproject.toml
setup.py
cipherloom/__init__.py
cipherloom/constants.py
cipherloom/polyalphabetic_ciphers.py
cipherloom/polygraphic_ciphers.py
cipherloom/substitution_ciphers.py
cipherloom/transposition_ciphers.py
cipherloom.egg-info/PKG-INFO
cipherloom.egg-info/SOURCES.txt
cipherloom.egg-info/dependency_links.txt
cipherloom.egg-info/requires.txt
cipherloom.egg-info/top_level.txt
cipherloom/utils/__init__.py
cipherloom/utils/base_cipher.py
cipherloom/utils/general_utils.py
cipherloom/utils/math_utils.py
cipherloom/utils/processing_utils.py
cipherloom/utils/string_utils.py
tests/test_ciphers.py