Metadata-Version: 2.1
Name: cipherloom
Version: 0.1.0
Summary: A collection of classical cipher implementations and utilities
Home-page: https://github.com/Vihaan314/Cipherloom
Author: Vihaan Mathur
Author-email: vihaan.mathur3141@gmail.com
Classifier: Programming Language :: Python :: 3
Classifier: License :: OSI Approved :: MIT License
Classifier: Operating System :: OS Independent
Requires-Python: >=3.9
